{"cameraMode":{"drawMode":0,"name":"Shaded","section":"Shading Mode"},"sceneLighting":false,"audioPlay":false,"sceneViewState":{"m_AlwaysRefresh":false,"showFog":true,"showSkybox":false,"showFlares":true,"showImageEffects":true,"showParticleSystems":true,"showVisualEffectGraphs":true,"m_FxEnabled":true},"in2DMode":false,"pivot":{"x":0.4886239767074585,"y":1.1885639429092408,"z":0.0},"rotation":{"x":0.27804723381996157,"y":-0.3236331045627594,"z":0.10011132061481476,"w":0.8988509178161621},"size":0.8660253882408142,"orthographic":true}